{
  "taskId": "260221-cody-dash-01-spike",
  "mode": "full",
  "pipeline": "spec_execute_verify",
  "startedAt": "2026-02-21T16:15:20.969Z",
  "updatedAt": "2026-02-21T16:15:20.972Z",
  "state": "running",
  "currentStage": null,
  "stages": {
    "taskify": {
      "state": "completed",
      "retries": 0,
      "outputFile": "task.json",
      "completedAt": "2026-02-21T16:15:20.971Z"
    },
    "spec": {
      "state": "completed",
      "retries": 0,
      "outputFile": "spec.md",
      "completedAt": "2026-02-21T16:15:20.971Z"
    },
    "gap": {
      "state": "completed",
      "retries": 0,
      "outputFile": "gap.md",
      "completedAt": "2026-02-21T16:15:20.972Z"
    }
  },
  "triggeredBy": "dispatch"
}